mcper/__init__.py
mcper-0.0.1.dist-info/licenses/LICENSE
mcper-0.0.1.dist-info/METADATA
mcper-0.0.1.dist-info/WHEEL
mcper-0.0.1.dist-info/top_level.txt
mcper-0.0.1.dist-info/RECORD
