Metadata-Version: 2.4
Name: mcper
Version: 0.0.1
Summary: This is a mcper.
Author-email: axiner <atpuxiner@163.com>
Project-URL: Homepage, https://github.com/atpuxiner/mcper
Classifier: Programming Language :: Python :: 3.11
Classifier: Operating System :: OS Independent
Requires-Python: >=3.11
License-File: LICENSE
Dynamic: license-file
